coolours/colour.py
coolours/coolours.py
coolours-0.6.dist-info/LICENSE.txt
coolours-0.6.dist-info/METADATA
coolours-0.6.dist-info/WHEEL
coolours-0.6.dist-info/top_level.txt
coolours-0.6.dist-info/RECORD
