Metadata-Version: 2.1
Name: coolours
Version: 0.6
Summary: A Python module to make text styling easy. Works in all versions of Python, build with escape codes and spaces.
Home-page: https://alexhawking.now.sh/
Author: Alex Hawking
Author-email: alexrhawking@gmail.com
License: MIT
Download-URL: https://github.com/Handmade-Studios/coolours-module/archive/master.zip
Keywords: colour,easy,output,terminal,colouring,color,cool,style,bold,underline
Platform: UNKNOWN
Classifier: Development Status :: 4 - Beta
Classifier: Intended Audience :: Developers
Classifier: Topic :: Software Development :: Build Tools
Classifier: License :: OSI Approved :: MIT License
Classifier: Programming Language :: Python :: 2.7
Classifier: Programming Language :: Python :: 3
Classifier: Programming Language :: Python :: 3.4
Classifier: Programming Language :: Python :: 3.5
Classifier: Programming Language :: Python :: 3.6
Classifier: Programming Language :: Python :: 3.7
